COPYING.txt
README.rst
pyproject.toml
src/WuttJamaican.egg-info/PKG-INFO
src/WuttJamaican.egg-info/SOURCES.txt
src/WuttJamaican.egg-info/dependency_links.txt
src/WuttJamaican.egg-info/entry_points.txt
src/WuttJamaican.egg-info/requires.txt
src/WuttJamaican.egg-info/top_level.txt
src/wuttjamaican/__init__.py
src/wuttjamaican/_version.py
src/wuttjamaican/app.py
src/wuttjamaican/conf.py
src/wuttjamaican/exc.py
src/wuttjamaican/testing.py
src/wuttjamaican/util.py
src/wuttjamaican/cmd/__init__.py
src/wuttjamaican/cmd/base.py
src/wuttjamaican/cmd/date_organize.py
src/wuttjamaican/cmd/make_appdir.py
src/wuttjamaican/cmd/setup.py
src/wuttjamaican/commands/__init__.py
src/wuttjamaican/commands/base.py
src/wuttjamaican/commands/make_appdir.py
src/wuttjamaican/commands/setup.py
src/wuttjamaican/db/__init__.py
src/wuttjamaican/db/conf.py
src/wuttjamaican/db/sess.py
tests/test_app.py
tests/test_conf.py
tests/test_util.py